{
    "numDocumentoIdObligado": "901756076",
    "numFactura": "FV3019",
    "tipoNota": null,
    "numNota": null,
    "usuarios": [
      {
        "tipoDocumentoIdentificacion": "CC",
        "numDocumentoIdentificacion": "1020734283",
        "tipoUsuario": "01",
        "fechaNacimiento": "1988-04-04",
        "codSexo": "F",
        "codPaisResidencia": "170",
        "codMunicipioResidencia": "11001",
        "codZonaTerritorialResidencia": "02",
        "incapacidad": "NO",
        "consecutivo": 1,
        "codPaisOrigen": "170",
        "servicios": {
          "procedimientos": [
            {
              "codPrestador": "110014051501",
              "fechaInicioAtencion": "2025-04-03 00:00",
              "idMIPRES": null,
              "numAutorizacion": "",
              "codProcedimiento": "890206",
              "viaIngresoServicioSalud": "02",
              "modalidadGrupoServicioTecSal": "01",
              "grupoServicios": "01",
              "codServicio": 407,
              "finalidadTecnologiaSalud": "12",
              "tipoDocumentoIdentificacion": "CC",
              "numDocumentoIdentificacion": "1020733311",
              "codDiagnosticoPrincipal": "K601",
              "codDiagnosticoRelacionado": null,
              "codComplicacion": null,
              "vrServicio": 250000,
              "conceptoRecaudo": "05",
              "valorPagoModerador": 0,
              "numFEVPagoModerador": null,
              "consecutivo": 1
            }
          ]
        }
      }
    ]
  }